{
  "year": "2008",
  "set_name": "Pokemon Diamond & Pearl Black Star Promo",
  "set_url": "https://www.psacard.com/pop/tcg-cards/2008/pokemon-diamond-pearl-black-star-promo/90095",
  "total_cards": 34,
  "cards": [
    {
      "pokemon_number": "N/A",
      "card_name": "TOTAL POPULATION",
      "base_name": "TOTAL POPULATION",
      "variety": "",
      "spec_id": 0,
      "psa_grades": {
        "psa_1": 60,
        "psa_2": 26,
        "psa_3": 64,
        "psa_4": 138,
        "psa_5": 367,
        "psa_6": 569,
        "psa_7": 719,
        "psa_8": 897,
        "psa_9": 628,
        "psa_10": 64,
        "psa_total": 3532
      },
      "grade_totals": {
        "total": 0,
        "grade_total": 3532
      }
    },
    {
      "pokemon_number": "DP16",
      "card_name": "Pikachu-Holo-Countdown Calendar",
      "base_name": "Pikachu-Holo",
      "variety": "Countdown Calendar",
      "spec_id": 2097116,
      "psa_grades": {
        "psa_1": 0,
        "psa_2": 0,
        "psa_3": 0,
        "psa_4": 1,
        "psa_5": 8,
        "psa_6": 12,
        "psa_7": 27,
        "psa_8": 19,
        "psa_9": 7,
        "psa_10": 0,
        "psa_total": 74
      },
      "grade_totals": {
        "total": 74,
        "grade_total": 74
      }
    },
    {
      "pokemon_number": "DP16",
      "card_name": "Pikachu-Holo-Countdown Calendar-French",
      "base_name": "Pikachu-Holo",
      "variety": "Countdown Calendar-French",
      "spec_id": 9211894,
      "psa_grades": {
        "psa_1": 0,
        "psa_2": 0,
        "psa_3": 0,
        "psa_4": 0,
        "psa_5": 0,
        "psa_6": 0,
        "psa_7": 1,
        "psa_8": 1,
        "psa_9": 0,
        "psa_10": 0,
        "psa_total": 2
      },
      "grade_totals": {
        "total": 2,
        "grade_total": 2
      }
    },
    {
      "pokemon_number": "DP16",
      "card_name": "Pikachu-Holo-Countdown Calendar-German",
      "base_name": "Pikachu-Holo",
      "variety": "Countdown Calendar-German",
      "spec_id": 9050966,
      "psa_grades": {
        "psa_1": 0,
        "psa_2": 0,
        "psa_3": 0,
        "psa_4": 0,
        "psa_5": 1,
        "psa_6": 4,
        "psa_7": 3,
        "psa_8": 2,
        "psa_9": 0,
        "psa_10": 0,
        "psa_total": 10
      },
      "grade_totals": {
        "total": 10,
        "grade_total": 10
      }
    },
    {
      "pokemon_number": "DP17",
      "card_name": "Dialga LV.X-Holo",
      "base_name": "Dialga LV.X-Holo",
      "variety": "",
      "spec_id": 1827434,
      "psa_grades": {
        "psa_1": 7,
        "psa_2": 5,
        "psa_3": 5,
        "psa_4": 13,
        "psa_5": 52,
        "psa_6": 57,
        "psa_7": 72,
        "psa_8": 90,
        "psa_9": 90,
        "psa_10": 6,
        "psa_total": 397
      },
      "grade_totals": {
        "total": 398,
        "grade_total": 397
      }
    },
    {
      "pokemon_number": "DP17",
      "card_name": "Dialga LV.X-Holo-Spring Tin-German",
      "base_name": "Dialga LV.X-Holo",
      "variety": "Spring Tin-German",
      "spec_id": 9679234,
      "psa_grades": {
        "psa_1": 0,
        "psa_2": 0,
        "psa_3": 0,
        "psa_4": 0,
        "psa_5": 0,
        "psa_6": 0,
        "psa_7": 0,
        "psa_8": 1,
        "psa_9": 0,
        "psa_10": 0,
        "psa_total": 1
      },
      "grade_totals": {
        "total": 1,
        "grade_total": 1
      }
    },
    {
      "pokemon_number": "DP18",
      "card_name": "Palkia LV.X-Holo",
      "base_name": "Palkia LV.X-Holo",
      "variety": "",
      "spec_id": 2301561,
      "psa_grades": {
        "psa_1": 9,
        "psa_2": 4,
        "psa_3": 9,
        "psa_4": 25,
        "psa_5": 58,
        "psa_6": 86,
        "psa_7": 92,
        "psa_8": 155,
        "psa_9": 73,
        "psa_10": 7,
        "psa_total": 518
      },
      "grade_totals": {
        "total": 518,
        "grade_total": 518
      }
    },
    {
      "pokemon_number": "DP18",
      "card_name": "Palkia LV.X-Holo-Spring Tin-German",
      "base_name": "Palkia LV.X-Holo",
      "variety": "Spring Tin-German",
      "spec_id": 8114900,
      "psa_grades": {
        "psa_1": 0,
        "psa_2": 0,
        "psa_3": 0,
        "psa_4": 0,
        "psa_5": 0,
        "psa_6": 2,
        "psa_7": 2,
        "psa_8": 2,
        "psa_9": 0,
        "psa_10": 0,
        "psa_total": 6
      },
      "grade_totals": {
        "total": 6,
        "grade_total": 6
      }
    },
    {
      "pokemon_number": "DP19",
      "card_name": "Darkrai LV.X-Holo",
      "base_name": "Darkrai LV.X-Holo",
      "variety": "",
      "spec_id": 2172840,
      "psa_grades": {
        "psa_1": 8,
        "psa_2": 1,
        "psa_3": 10,
        "psa_4": 28,
        "psa_5": 70,
        "psa_6": 97,
        "psa_7": 121,
        "psa_8": 159,
        "psa_9": 88,
        "psa_10": 20,
        "psa_total": 602
      },
      "grade_totals": {
        "total": 605,
        "grade_total": 602
      }
    },
    {
      "pokemon_number": "DP19",
      "card_name": "Darkrai LV.X-Holo-Spring Tin-German",
      "base_name": "Darkrai LV.X-Holo",
      "variety": "Spring Tin-German",
      "spec_id": 7145669,
      "psa_grades": {
        "psa_1": 0,
        "psa_2": 0,
        "psa_3": 0,
        "psa_4": 0,
        "psa_5": 0,
        "psa_6": 4,
        "psa_7": 0,
        "psa_8": 2,
        "psa_9": 2,
        "psa_10": 0,
        "psa_total": 8
      },
      "grade_totals": {
        "total": 8,
        "grade_total": 8
      }
    },
    {
      "pokemon_number": "DP20",
      "card_name": "Magmortar-Holo",
      "base_name": "Magmortar-Holo",
      "variety": "",
      "spec_id": 2391047,
      "psa_grades": {
        "psa_1": 0,
        "psa_2": 0,
        "psa_3": 0,
        "psa_4": 2,
        "psa_5": 4,
        "psa_6": 8,
        "psa_7": 9,
        "psa_8": 9,
        "psa_9": 10,
        "psa_10": 3,
        "psa_total": 45
      },
      "grade_totals": {
        "total": 45,
        "grade_total": 45
      }
    },
    {
      "pokemon_number": "DP21",
      "card_name": "Raichu-Holo",
      "base_name": "Raichu-Holo",
      "variety": "",
      "spec_id": 880186,
      "psa_grades": {
        "psa_1": 2,
        "psa_2": 2,
        "psa_3": 1,
        "psa_4": 0,
        "psa_5": 7,
        "psa_6": 8,
        "psa_7": 20,
        "psa_8": 27,
        "psa_9": 20,
        "psa_10": 8,
        "psa_total": 95
      },
      "grade_totals": {
        "total": 97,
        "grade_total": 95
      }
    },
    {
      "pokemon_number": "DP22",
      "card_name": "Mime Jr.-Holo",
      "base_name": "Mime Jr.-Holo",
      "variety": "",
      "spec_id": 2339894,
      "psa_grades": {
        "psa_1": 0,
        "psa_2": 0,
        "psa_3": 0,
        "psa_4": 1,
        "psa_5": 3,
        "psa_6": 2,
        "psa_7": 8,
        "psa_8": 8,
        "psa_9": 3,
        "psa_10": 1,
        "psa_total": 26
      },
      "grade_totals": {
        "total": 26,
        "grade_total": 26
      }
    },
    {
      "pokemon_number": "DP23",
      "card_name": "Glameow-Holo",
      "base_name": "Glameow-Holo",
      "variety": "",
      "spec_id": 2356555,
      "psa_grades": {
        "psa_1": 0,
        "psa_2": 0,
        "psa_3": 0,
        "psa_4": 0,
        "psa_5": 1,
        "psa_6": 2,
        "psa_7": 4,
        "psa_8": 4,
        "psa_9": 12,
        "psa_10": 0,
        "psa_total": 23
      },
      "grade_totals": {
        "total": 23,
        "grade_total": 23
      }
    },
    {
      "pokemon_number": "DP24",
      "card_name": "Darkrai",
      "base_name": "Darkrai",
      "variety": "",
      "spec_id": 2228128,
      "psa_grades": {
        "psa_1": 0,
        "psa_2": 0,
        "psa_3": 0,
        "psa_4": 3,
        "psa_5": 6,
        "psa_6": 5,
        "psa_7": 5,
        "psa_8": 22,
        "psa_9": 15,
        "psa_10": 0,
        "psa_total": 56
      },
      "grade_totals": {
        "total": 56,
        "grade_total": 56
      }
    },
    {
      "pokemon_number": "DP24",
      "card_name": "Darkrai-Holo-Darkrai Premium Box",
      "base_name": "Darkrai-Holo",
      "variety": "Darkrai Premium Box",
      "spec_id": 2859893,
      "psa_grades": {
        "psa_1": 0,
        "psa_2": 0,
        "psa_3": 2,
        "psa_4": 5,
        "psa_5": 5,
        "psa_6": 5,
        "psa_7": 11,
        "psa_8": 15,
        "psa_9": 10,
        "psa_10": 0,
        "psa_total": 53
      },
      "grade_totals": {
        "total": 53,
        "grade_total": 53
      }
    },
    {
      "pokemon_number": "DP26",
      "card_name": "Dialga-Holo",
      "base_name": "Dialga-Holo",
      "variety": "",
      "spec_id": 1827412,
      "psa_grades": {
        "psa_1": 1,
        "psa_2": 0,
        "psa_3": 1,
        "psa_4": 5,
        "psa_5": 9,
        "psa_6": 21,
        "psa_7": 30,
        "psa_8": 34,
        "psa_9": 66,
        "psa_10": 3,
        "psa_total": 170
      },
      "grade_totals": {
        "total": 170,
        "grade_total": 170
      }
    },
    {
      "pokemon_number": "DP27",
      "card_name": "Palkia-Holo",
      "base_name": "Palkia-Holo",
      "variety": "",
      "spec_id": 2169943,
      "psa_grades": {
        "psa_1": 1,
        "psa_2": 1,
        "psa_3": 1,
        "psa_4": 4,
        "psa_5": 15,
        "psa_6": 20,
        "psa_7": 11,
        "psa_8": 27,
        "psa_9": 34,
        "psa_10": 1,
        "psa_total": 115
      },
      "grade_totals": {
        "total": 117,
        "grade_total": 115
      }
    },
    {
      "pokemon_number": "DP28",
      "card_name": "Mewtu LV.X-Holo-Fall Tin-German",
      "base_name": "Mewtu LV.X-Holo",
      "variety": "Fall Tin-German",
      "spec_id": 10226288,
      "psa_grades": {
        "psa_1": 0,
        "psa_2": 0,
        "psa_3": 0,
        "psa_4": 0,
        "psa_5": 3,
        "psa_6": 1,
        "psa_7": 0,
        "psa_8": 1,
        "psa_9": 1,
        "psa_10": 0,
        "psa_total": 6
      },
      "grade_totals": {
        "total": 6,
        "grade_total": 6
      }
    },
    {
      "pokemon_number": "DP28",
      "card_name": "Mewtwo LV.X-Holo",
      "base_name": "Mewtwo LV.X-Holo",
      "variety": "",
      "spec_id": 880381,
      "psa_grades": {
        "psa_1": 16,
        "psa_2": 9,
        "psa_3": 17,
        "psa_4": 27,
        "psa_5": 65,
        "psa_6": 108,
        "psa_7": 126,
        "psa_8": 126,
        "psa_9": 52,
        "psa_10": 6,
        "psa_total": 552
      },
      "grade_totals": {
        "total": 560,
        "grade_total": 552
      }
    },
    {
      "pokemon_number": "DP29",
      "card_name": "Rhyperior LV.X-Holo",
      "base_name": "Rhyperior LV.X-Holo",
      "variety": "",
      "spec_id": 2189058,
      "psa_grades": {
        "psa_1": 7,
        "psa_2": 2,
        "psa_3": 5,
        "psa_4": 4,
        "psa_5": 15,
        "psa_6": 31,
        "psa_7": 50,
        "psa_8": 51,
        "psa_9": 22,
        "psa_10": 1,
        "psa_total": 188
      },
      "grade_totals": {
        "total": 190,
        "grade_total": 188
      }
    },
    {
      "pokemon_number": "DP29",
      "card_name": "Rihornior LV.X-Holo-Fall Tin-German",
      "base_name": "Rihornior LV.X-Holo",
      "variety": "Fall Tin-German",
      "spec_id": 9679242,
      "psa_grades": {
        "psa_1": 0,
        "psa_2": 0,
        "psa_3": 0,
        "psa_4": 0,
        "psa_5": 1,
        "psa_6": 1,
        "psa_7": 0,
        "psa_8": 0,
        "psa_9": 0,
        "psa_10": 0,
        "psa_total": 2
      },
      "grade_totals": {
        "total": 2,
        "grade_total": 2
      }
    },
    {
      "pokemon_number": "DP30",
      "card_name": "Regigigas LV.X-Holo",
      "base_name": "Regigigas LV.X",
      "variety": "Holo",
      "spec_id": 1785826,
      "psa_grades": {
        "psa_1": 5,
        "psa_2": 0,
        "psa_3": 6,
        "psa_4": 11,
        "psa_5": 23,
        "psa_6": 52,
        "psa_7": 66,
        "psa_8": 74,
        "psa_9": 63,
        "psa_10": 4,
        "psa_total": 304
      },
      "grade_totals": {
        "total": 305,
        "grade_total": 304
      }
    },
    {
      "pokemon_number": "DP30",
      "card_name": "Regigigas LV.X-Holo-Holiday Tin-German",
      "base_name": "Regigigas LV.X-Holo",
      "variety": "Holiday Tin-German",
      "spec_id": 9679286,
      "psa_grades": {
        "psa_1": 0,
        "psa_2": 0,
        "psa_3": 1,
        "psa_4": 0,
        "psa_5": 0,
        "psa_6": 1,
        "psa_7": 0,
        "psa_8": 0,
        "psa_9": 0,
        "psa_10": 0,
        "psa_total": 2
      },
      "grade_totals": {
        "total": 2,
        "grade_total": 2
      }
    },
    {
      "pokemon_number": "DP31",
      "card_name": "Heatran LV.X-Holo",
      "base_name": "Heatran LV.X-Holo",
      "variety": "",
      "spec_id": 1971924,
      "psa_grades": {
        "psa_1": 3,
        "psa_2": 2,
        "psa_3": 6,
        "psa_4": 7,
        "psa_5": 15,
        "psa_6": 32,
        "psa_7": 47,
        "psa_8": 34,
        "psa_9": 19,
        "psa_10": 0,
        "psa_total": 165
      },
      "grade_totals": {
        "total": 169,
        "grade_total": 165
      }
    },
    {
      "pokemon_number": "DP32",
      "card_name": "Magnezone-Holo",
      "base_name": "Magnezone-Holo",
      "variety": "",
      "spec_id": 880192,
      "psa_grades": {
        "psa_1": 0,
        "psa_2": 0,
        "psa_3": 0,
        "psa_4": 0,
        "psa_5": 1,
        "psa_6": 4,
        "psa_7": 3,
        "psa_8": 13,
        "psa_9": 13,
        "psa_10": 2,
        "psa_total": 36
      },
      "grade_totals": {
        "total": 36,
        "grade_total": 36
      }
    },
    {
      "pokemon_number": "DP33",
      "card_name": "Dusknoir-Holo",
      "base_name": "Dusknoir-Holo",
      "variety": "",
      "spec_id": 1789855,
      "psa_grades": {
        "psa_1": 1,
        "psa_2": 0,
        "psa_3": 0,
        "psa_4": 0,
        "psa_5": 3,
        "psa_6": 3,
        "psa_7": 5,
        "psa_8": 13,
        "psa_9": 24,
        "psa_10": 1,
        "psa_total": 50
      },
      "grade_totals": {
        "total": 50,
        "grade_total": 50
      }
    },
    {
      "pokemon_number": "DP34",
      "card_name": "Drifblim-Holo",
      "base_name": "Drifblim-Holo",
      "variety": "",
      "spec_id": 2356565,
      "psa_grades": {
        "psa_1": 0,
        "psa_2": 0,
        "psa_3": 0,
        "psa_4": 1,
        "psa_5": 0,
        "psa_6": 0,
        "psa_7": 5,
        "psa_8": 4,
        "psa_9": 3,
        "psa_10": 1,
        "psa_total": 14
      },
      "grade_totals": {
        "total": 14,
        "grade_total": 14
      }
    }
  ]
}